.editorconfig
.pre-commit-config.yaml
CHANGELOG.rst
CONTRIBUTING.rst
LICENSE
Makefile
README.rst
multivar_horner/__init__.py
multivar_horner/_numba_replacements.py
multivar_horner/c_evaluation.py
multivar_horner/classes/__init__.py
multivar_horner/classes/abstract_poly.py
multivar_horner/classes/factorisation.py
multivar_horner/classes/helpers.py
multivar_horner/classes/horner_poly.py
multivar_horner/classes/regular_poly.py
multivar_horner/global_settings.py
multivar_horner/helper_fcts.py
multivar_horner/helpers_fcts_numba.py
tests/__init__.py
tests/helpers.py
tests/hypothesis_tests.py
tests/main_test.py
tests/plotting.py
tests/settings.py
tox.ini
multivar_horner-3.1.0.dist-info/METADATA
multivar_horner-3.1.0.dist-info/WHEEL
multivar_horner-3.1.0.dist-info/LICENSE
multivar_horner-3.1.0.dist-info/RECORD
