Metadata-Version: 2.1
Name: multivar-horner
Version: 3.1.0
Summary: python package implementing a multivariate Horner scheme for efficiently evaluating multivariate polynomials
Home-page: https://multivar-horner.readthedocs.io/en/latest/
License: MIT
Keywords: mathematics,polynomials,evaluation,multivariate,horner-scheme
Author: jannikmi
Author-email: github@michelfe.it
Requires-Python: >=3.8,<4
Classifier: Development Status :: 5 - Production/Stable
Classifier: Intended Audience :: Developers
Classifier: Intended Audience :: Information Technology
Classifier: Intended Audience :: Science/Research
Classifier: License :: OSI Approved :: MIT License
Classifier: Natural Language :: English
Classifier: Operating System :: OS Independent
Classifier: Programming Language :: Python :: 3
Classifier: Programming Language :: Python :: 3.8
Classifier: Programming Language :: Python :: 3.9
Classifier: Programming Language :: Python :: 3.10
Classifier: Programming Language :: Python :: 3.11
Classifier: Topic :: Scientific/Engineering
Classifier: Topic :: Scientific/Engineering :: Mathematics
Classifier: Topic :: Scientific/Engineering :: Physics
Provides-Extra: numba
Requires-Dist: numba (>=0.56,<1) ; extra == "numba"
Requires-Dist: numpy (>=1.18,<2)
Project-URL: Documentation, https://multivar-horner.readthedocs.io/en/latest/
Project-URL: Repository, https://github.com/jannikmi/multivar_horner
